quntoken/__init__.py
quntoken/__main__.py
quntoken/qt_convjson
quntoken/qt_convspl
quntoken/qt_convtsv
quntoken/qt_convxml
quntoken/qt_hyphen
quntoken/qt_preproc
quntoken/qt_snt
quntoken/qt_sntcorr
quntoken/qt_token
quntoken/quntoken.py
quntoken/version.py
quntoken-3.3.2.dist-info/LICENSE.txt
quntoken-3.3.2.dist-info/METADATA
quntoken-3.3.2.dist-info/WHEEL
quntoken-3.3.2.dist-info/entry_points.txt
quntoken-3.3.2.dist-info/top_level.txt
quntoken-3.3.2.dist-info/RECORD
