Metadata-Version: 2.1
Name: quntoken
Version: 3.3.2
Summary: Hungarian tokenizer based on quex and huntoken.
Home-page: https://github.com/dlt-rilmta/quntoken
Author: mittelholcz
License: UNKNOWN
Platform: UNKNOWN
Classifier: Programming Language :: Python :: 3
Classifier: License :: OSI Approved :: GNU General Public License v3 (GPLv3)
Classifier: Operating System :: POSIX :: Linux
Requires-Python: >=3.6
